elasticsearch_synonym_toolkit-0.2.3.dist-info/DESCRIPTION.rst
elasticsearch_synonym_toolkit-0.2.3.dist-info/METADATA
elasticsearch_synonym_toolkit-0.2.3.dist-info/RECORD
elasticsearch_synonym_toolkit-0.2.3.dist-info/WHEEL
elasticsearch_synonym_toolkit-0.2.3.dist-info/entry_points.txt
elasticsearch_synonym_toolkit-0.2.3.dist-info/metadata.json
elasticsearch_synonym_toolkit-0.2.3.dist-info/top_level.txt
es_synonyms/__init__.py
es_synonyms/__main__.py
es_synonyms/constants.py
es_synonyms/exceptions.py
es_synonyms/parser.py
es_synonyms/report.py
es_synonyms/synlint.py
es_synonyms/tests.py
es_synonyms/utils.py
