Metadata-Version: 1.1
Name: elasticsearch-synonym-toolkit
Version: 0.2.3
Summary: Toolkit for Elasticsearch Synonym files.
Home-page: https://github.com/prashnts/elasticsearch-synonyms
Author: Prashant Sinha
Author-email: prashant+git@noop.pw
License: MIT
Download-URL: https://github.com/prashnts/elasticsearch-synonym/tarball/0.2.3
Keywords: elasticsearch-synonym-toolkit
Platform: UNKNOWN
Classifier: Development Status :: 3 - Alpha
Classifier: Intended Audience :: Developers
Classifier: License :: OSI Approved :: MIT License
Classifier: Natural Language :: English
Classifier: Programming Language :: Python :: 2
Classifier: Programming Language :: Python :: 2.7
Classifier: Programming Language :: Python :: 3
Classifier: Programming Language :: Python :: 3.2
Classifier: Programming Language :: Python :: 3.3
Classifier: Programming Language :: Python :: 3.4
Classifier: Programming Language :: Python :: 3.5
